sksfa/__init__.py
sksfa/_hsfa.py
sksfa/_sfa.py
sksfa/_version.py
sksfa/tests/__init__.py
sksfa/tests/test_common.py
sksfa/tests/test_sfa.py
sksfa/utils/__init__.py
sksfa/utils/_recfield.py
sksfa/utils/_utils.py
sklearn_sfa-0.1.6.dist-info/LICENSE
sklearn_sfa-0.1.6.dist-info/METADATA
sklearn_sfa-0.1.6.dist-info/WHEEL
sklearn_sfa-0.1.6.dist-info/top_level.txt
sklearn_sfa-0.1.6.dist-info/RECORD
